{
  "_class": "shapePath",
  "booleanOperation": -1,
  "clippingMaskMode": 0,
  "do_objectID": "8DFEC8E4-338B-46C7-91CF-4E242DAEDF46",
  "edited": true,
  "exportOptions": {
    "_class": "exportOptions",
    "exportFormats": [
    ],
    "includedLayerIds": [
    ],
    "layerOptions": 0,
    "shouldTrim": false
  },
  "frame": {
    "_class": "rect",
    "constrainProportions": false,
    "height": 24.77277164109237,
    "width": 16.83446634655432,
    "x": -2.220446082337538e-17,
    "y": 2.309263925631039e-15
  },
  "hasClippingMask": false,
  "isClosed": false,
  "isFixedToViewport": false,
  "isFlippedHorizontal": false,
  "isFlippedVertical": false,
  "isLocked": false,
  "isVisible": true,
  "layerListExpandedType": 0,
  "name": "Path",
  "nameIsFixed": false,
  "pointRadiusBehaviour": 1,
  "points": [
    {
      "_class": "curvePoint",
      "cornerRadius": 0,
      "curveFrom": "{0.68606691355492444, 0.030517370202217287}",
      "curveMode": 4,
      "curveTo": "{0.78149019522408314, 0.0064586973368661168}",
      "hasCurveFrom": true,
      "hasCurveTo": false,
      "point": "{0.78149019522408314, 0.0064586973368661168}"
    },
    {
      "_class": "curvePoint",
      "cornerRadius": 0,
      "curveFrom": "{0.49883198836743176, 0.31888236261987357}",
      "curveMode": 3,
      "curveTo": "{0.63567030488453469, 0.10745668309040436}",
      "hasCurveFrom": true,
      "hasCurveTo": true,
      "point": "{0.59290090573003118, 0.17351307952809014}"
    },
    {
      "_class": "curvePoint",
      "cornerRadius": 0,
      "curveFrom": "{0.19481284271083688, 0.67023586701587579}",
      "curveMode": 3,
      "curveTo": "{0.38242794033525845, 0.45343331630240519}",
      "hasCurveFrom": true,
      "hasCurveTo": true,
      "point": "{0.26901775024390029, 0.58449656975747633}"
    },
    {
      "_class": "curvePoint",
      "cornerRadius": 0,
      "curveFrom": "{0.031077326281013111, 0.85945975111591022}",
      "curveMode": 3,
      "curveTo": "{0.12172469171125219, 0.75469957020960221}",
      "hasCurveFrom": true,
      "hasCurveTo": true,
      "point": "{0.049705775690530127, 0.83791997285928033}"
    },
    {
      "_class": "curvePoint",
      "cornerRadius": 0,
      "curveFrom": "{-0.0042311887987603438, 0.92797045512106813}",
      "curveMode": 2,
      "curveTo": "{0.012258790653031581, 0.88132246457878649}",
      "hasCurveFrom": true,
      "hasCurveTo": true,
      "point": "{0.0039900401498276167, 0.90471912027133272}"
    },
    {
      "_class": "curvePoint",
      "cornerRadius": 0,
      "curveFrom": "{0.041627111405790507, 0.98362833791762239}",
      "curveMode": 2,
      "curveTo": "{-0.00050074676139524052, 0.95335316233202938}",
      "hasCurveFrom": true,
      "hasCurveTo": true,
      "point": "{0.022262077899723749, 0.96970983052840576}"
    },
    {
      "_class": "curvePoint",
      "cornerRadius": 0,
      "curveFrom": "{0.12013271963161234, 0.99769216614964995}",
      "curveMode": 2,
      "curveTo": "{0.071494408482018837, 0.98915052994443453}",
      "hasCurveFrom": true,
      "hasCurveTo": true,
      "point": "{0.099888537365147481, 0.99413987888094035}"
    },
    {
      "_class": "curvePoint",
      "cornerRadius": 0,
      "curveFrom": "{0.18409673214490296, 0.99786978051308528}",
      "curveMode": 2,
      "curveTo": "{0.14092339977616261, 1.0012606001786717}",
      "hasCurveFrom": true,
      "hasCurveTo": true,
      "point": "{0.16252194634918679, 0.99956519034587854}"
    },
    {
      "_class": "curvePoint",
      "cornerRadius": 0,
      "curveFrom": "{0.21612625995616436, 0.9763300022564555}",
      "curveMode": 4,
      "curveTo": "{0.20704964302448647, 0.98963493275380399}",
      "hasCurveFrom": false,
      "hasCurveTo": true,
      "point": "{0.21612625995616436, 0.9763300022564555}"
    },
    {
      "_class": "curvePoint",
      "cornerRadius": 0,
      "curveFrom": "{0.24528073371315084, 1.0004048218821191}",
      "curveMode": 4,
      "curveTo": "{0.22985998924022155, 0.97529660959646725}",
      "hasCurveFrom": true,
      "hasCurveTo": false,
      "point": "{0.22985998924022155, 0.97529660959646725}"
    },
    {
      "_class": "curvePoint",
      "cornerRadius": 0,
      "curveFrom": "{0.37404038594551414, 0.95532306709013193}",
      "curveMode": 2,
      "curveTo": "{0.30708251549140825, 0.9966910670102862}",
      "hasCurveFrom": true,
      "hasCurveTo": true,
      "point": "{0.34051392916384504, 0.97603936057083374}"
    },
    {
      "_class": "curvePoint",
      "cornerRadius": 0,
      "curveFrom": "{0.48010849584868259, 0.76800450070695081}",
      "curveMode": 3,
      "curveTo": "{0.38770283289764712, 0.92538697347109755}",
      "hasCurveFrom": true,
      "hasCurveTo": true,
      "point": "{0.40402648690828263, 0.89759839897360139}"
    },
    {
      "_class": "curvePoint",
      "cornerRadius": 0,
      "curveFrom": "{0.83423912084797069, 0.44828249976277623}",
      "curveMode": 3,
      "curveTo": "{0.63947202925382374, 0.660241022382552}",
      "hasCurveFrom": true,
      "hasCurveTo": true,
      "point": "{0.75478308152982654, 0.53473225447491768}"
    },
    {
      "_class": "curvePoint",
      "cornerRadius": 0,
      "curveFrom": "{0.96763212465540505, 0.23233572734585836}",
      "curveMode": 3,
      "curveTo": "{0.89309456624002892, 0.35306505420104717}",
      "hasCurveFrom": true,
      "hasCurveTo": true,
      "point": "{0.95259155261940487, 0.25671733541745601}"
    },
    {
      "_class": "curvePoint",
      "cornerRadius": 0,
      "curveFrom": "{1.008524422402572, 0.1335014074741705}",
      "curveMode": 3,
      "curveTo": "{0.98286278290986984, 0.20766347758863921}",
      "hasCurveFrom": true,
      "hasCurveTo": true,
      "point": "{0.99172555284577535, 0.18203856897299323}"
    },
    {
      "_class": "curvePoint",
      "cornerRadius": 0,
      "curveFrom": "{0.92182134600547039, 0.0073629159143557867}",
      "curveMode": 2,
      "curveTo": "{1.0003982365632162, 0.081169757301953457}",
      "hasCurveFrom": true,
      "hasCurveTo": true,
      "point": "{0.96133551866876987, 0.04446817111205862}"
    },
    {
      "_class": "curvePoint",
      "cornerRadius": 0,
      "curveFrom": "{0.78149019522408314, 0.0064586973368661168}",
      "curveMode": 4,
      "curveTo": "{0.84887575966973405, -0.010543841272003108}",
      "hasCurveFrom": false,
      "hasCurveTo": true,
      "point": "{0.78149019522408314, 0.0064586973368661168}"
    }
  ],
  "resizingConstraint": 63,
  "resizingType": 0,
  "rotation": 0,
  "shouldBreakMaskChain": false,
  "style": {
    "_class": "style",
    "blur": {
      "_class": "blur",
      "center": "{0.5, 0.5}",
      "isEnabled": false,
      "motionAngle": 0,
      "radius": 4.000000059604645,
      "saturation": 1,
      "type": 0
    },
    "borderOptions": {
      "_class": "borderOptions",
      "dashPattern": [
      ],
      "isEnabled": true,
      "lineCapStyle": 0,
      "lineJoinStyle": 0
    },
    "borders": [
    ],
    "colorControls": {
      "_class": "colorControls",
      "brightness": 0,
      "contrast": 1,
      "hue": 0,
      "isEnabled": false,
      "saturation": 1
    },
    "contextSettings": {
      "_class": "graphicsContextSettings",
      "blendMode": 0,
      "opacity": 1
    },
    "do_objectID": "75E737B6-54B0-42B6-BF11-033AAD360776",
    "endMarkerType": 0,
    "fills": [
    ],
    "innerShadows": [
    ],
    "miterLimit": 10,
    "shadows": [
    ],
    "startMarkerType": 0,
    "windingRule": 1
  }
}