{
  "_class": "shapePath",
  "booleanOperation": -1,
  "clippingMaskMode": 0,
  "do_objectID": "7D5110DD-15BE-4108-8622-ADBB0A58A021",
  "edited": true,
  "exportOptions": {
    "_class": "exportOptions",
    "exportFormats": [
    ],
    "includedLayerIds": [
    ],
    "layerOptions": 0,
    "shouldTrim": false
  },
  "frame": {
    "_class": "rect",
    "constrainProportions": false,
    "height": 3.610896602693003,
    "width": 13.33841562597678,
    "x": 459.6433781282099,
    "y": 251.9161597137393
  },
  "hasClippingMask": false,
  "isClosed": true,
  "isFixedToViewport": false,
  "isFlippedHorizontal": false,
  "isFlippedVertical": false,
  "isLocked": false,
  "isVisible": true,
  "layerListExpandedType": 0,
  "name": "Path",
  "nameIsFixed": false,
  "pointRadiusBehaviour": 1,
  "points": [
    {
      "_class": "curvePoint",
      "cornerRadius": 0,
      "curveFrom": "{0.49789263056501426, 0.83629771212634318}",
      "curveMode": 4,
      "curveTo": "{0.31091452782832857, 0.83629771212634318}",
      "hasCurveFrom": true,
      "hasCurveTo": false,
      "point": "{0.31091452782832857, 0.83629771212634318}"
    },
    {
      "_class": "curvePoint",
      "cornerRadius": 0,
      "curveFrom": "{0.90288173617944711, 0.81466304853070526}",
      "curveMode": 3,
      "curveTo": "{0.67569748609019298, 0.85504775390923626}",
      "hasCurveFrom": true,
      "hasCurveTo": true,
      "point": "{0.85291681519761864, 0.82331691396896045}"
    },
    {
      "_class": "curvePoint",
      "cornerRadius": 0,
      "curveFrom": "{1.0061295611770527, 0.53341242178743298}",
      "curveMode": 3,
      "curveTo": "{0.95362735905161478, 0.67187426879950529}",
      "hasCurveFrom": true,
      "hasCurveTo": true,
      "point": "{0.99734666491071255, 0.55648939628943306}"
    },
    {
      "_class": "curvePoint",
      "cornerRadius": 0,
      "curveFrom": "{0.92669314383484691, 0.20961362330605562}",
      "curveMode": 3,
      "curveTo": "{0.99149140073315989, 0.28172916862484182}",
      "hasCurveFrom": true,
      "hasCurveTo": true,
      "point": "{0.97704841576184775, 0.26586374865471418}"
    },
    {
      "_class": "curvePoint",
      "cornerRadius": 0,
      "curveFrom": "{0.67198915211107735, 0.51971046817685884}",
      "curveMode": 3,
      "curveTo": "{0.8581865529574183, 0.12595959073626939}",
      "hasCurveFrom": true,
      "hasCurveTo": true,
      "point": "{0.82051768674846493, 0.2060078460401194}"
    },
    {
      "_class": "curvePoint",
      "cornerRadius": 0,
      "curveFrom": "{0.3329693562304637, -0.039185008043770092}",
      "curveMode": 3,
      "curveTo": "{0.55078518363562456, 0.33148889489481931}",
      "hasCurveFrom": true,
      "hasCurveTo": true,
      "point": "{0.41221059810008331, 0.096392217155557403}"
    },
    {
      "_class": "curvePoint",
      "cornerRadius": 0,
      "curveFrom": "{0.082949575848740784, 0.10648839350018501}",
      "curveMode": 3,
      "curveTo": "{0.22171933685686271, -0.013944567182195947}",
      "hasCurveFrom": true,
      "hasCurveTo": true,
      "point": "{0.13271932135798303, 0.06321906630890918}"
    },
    {
      "_class": "curvePoint",
      "cornerRadius": 0,
      "curveFrom": "{0.067140362569330772, 0.78148989768406729}",
      "curveMode": 4,
      "curveTo": "{0.049574570036656052, 0.40360444021360548}",
      "hasCurveFrom": true,
      "hasCurveTo": true,
      "point": "{0, 0.62572031979547438}"
    },
    {
      "_class": "curvePoint",
      "cornerRadius": 0,
      "curveFrom": "{0.16941231020401096, 0.75480714591611053}",
      "curveMode": 4,
      "curveTo": "{0.11105484390101478, 0.88389397203674658}",
      "hasCurveFrom": true,
      "hasCurveTo": true,
      "point": "{0.16062941393767638, 1}"
    },
    {
      "_class": "curvePoint",
      "cornerRadius": 0,
      "curveFrom": "{0.19517547258526721, 0.38773902024347784}",
      "curveMode": 4,
      "curveTo": "{0.17604827627190844, 0.57668174897870883}",
      "hasCurveFrom": true,
      "hasCurveTo": true,
      "point": "{0.1824890668672253, 0.39711404113491411}"
    },
    {
      "_class": "curvePoint",
      "cornerRadius": 0,
      "curveFrom": "{0.25392328983343027, 0.5384605099597416}",
      "curveMode": 4,
      "curveTo": "{0.20825222924848155, 0.37764284389884001}",
      "hasCurveFrom": true,
      "hasCurveTo": true,
      "point": "{0.22113381043910965, 0.36826782300739347}"
    },
    {
      "_class": "curvePoint",
      "cornerRadius": 0,
      "curveFrom": "{0.31091452782832857, 0.83629771212634318}",
      "curveMode": 4,
      "curveTo": "{0.2867127692277564, 0.70937435236528112}",
      "hasCurveFrom": false,
      "hasCurveTo": true,
      "point": "{0.31091452782832857, 0.83629771212634318}"
    }
  ],
  "resizingConstraint": 63,
  "resizingType": 0,
  "rotation": 0,
  "shouldBreakMaskChain": false,
  "style": {
    "_class": "style",
    "blur": {
      "_class": "blur",
      "center": "{0.5, 0.5}",
      "isEnabled": false,
      "motionAngle": 0,
      "radius": 10,
      "saturation": 1,
      "type": 0
    },
    "borderOptions": {
      "_class": "borderOptions",
      "dashPattern": [
      ],
      "isEnabled": true,
      "lineCapStyle": 0,
      "lineJoinStyle": 0
    },
    "borders": [
    ],
    "colorControls": {
      "_class": "colorControls",
      "brightness": 0,
      "contrast": 1,
      "hue": 0,
      "isEnabled": false,
      "saturation": 1
    },
    "contextSettings": {
      "_class": "graphicsContextSettings",
      "blendMode": 0,
      "opacity": 1
    },
    "do_objectID": "A03FFFDD-38DA-4A43-9AFA-6AD0C2AEB75E",
    "endMarkerType": 0,
    "fills": [
    ],
    "innerShadows": [
    ],
    "miterLimit": 10,
    "shadows": [
    ],
    "startMarkerType": 0,
    "windingRule": 1
  }
}