{
  "_class": "shapePath",
  "booleanOperation": -1,
  "clippingMaskMode": 0,
  "do_objectID": "92502E85-2D74-449D-900D-F3167330FCCD",
  "edited": true,
  "exportOptions": {
    "_class": "exportOptions",
    "exportFormats": [
    ],
    "includedLayerIds": [
    ],
    "layerOptions": 0,
    "shouldTrim": false
  },
  "frame": {
    "_class": "rect",
    "constrainProportions": false,
    "height": 2.879383620483279,
    "width": 2.388851735639396,
    "x": 7.479349636243469e-16,
    "y": -2.259428599272264e-16
  },
  "hasClippingMask": false,
  "isClosed": true,
  "isFixedToViewport": false,
  "isFlippedHorizontal": false,
  "isFlippedVertical": false,
  "isLocked": false,
  "isVisible": true,
  "layerListExpandedType": 0,
  "name": "Path",
  "nameIsFixed": false,
  "pointRadiusBehaviour": 1,
  "points": [
    {
      "_class": "curvePoint",
      "cornerRadius": 0,
      "curveFrom": "{-0.0011474195001011491, 0.70220940219488748}",
      "curveMode": 4,
      "curveTo": "{0.001366048808603106, 0.70942765754556203}",
      "hasCurveFrom": true,
      "hasCurveTo": false,
      "point": "{0.001366048808603106, 0.70942765754556203}"
    },
    {
      "_class": "curvePoint",
      "cornerRadius": 0,
      "curveFrom": "{0.0041695326913886738, 0.68817390567968773}",
      "curveMode": 4,
      "curveTo": "{-0.00018070091982964767, 0.69507134968144302}",
      "hasCurveFrom": false,
      "hasCurveTo": true,
      "point": "{0.0041695326913886738, 0.68817390567968773}"
    },
    {
      "_class": "curvePoint",
      "cornerRadius": 0,
      "curveFrom": "{0.44015961239361323, 0.0090964828557001422}",
      "curveMode": 4,
      "curveTo": "{0.43532601949225846, 0.016635549555292777}",
      "hasCurveFrom": true,
      "hasCurveTo": false,
      "point": "{0.43532601949225846, 0.016635549555292777}"
    },
    {
      "_class": "curvePoint",
      "cornerRadius": 0,
      "curveFrom": "{0.46326418646209072, -0.0010090746352441917}",
      "curveMode": 4,
      "curveTo": "{0.44673329873945589, 0.0040437041102279756}",
      "hasCurveFrom": true,
      "hasCurveTo": true,
      "point": "{0.45495040667176023, 0.0014772133188774136}"
    },
    {
      "_class": "curvePoint",
      "cornerRadius": 0,
      "curveFrom": "{0.48056844904894197, 0.0034822842496201475}",
      "curveMode": 4,
      "curveTo": "{0.47177130996847499, -0.00036745193740626608}",
      "hasCurveFrom": false,
      "hasCurveTo": true,
      "point": "{0.48056844904894197, 0.0034822842496201475}"
    },
    {
      "_class": "curvePoint",
      "cornerRadius": 0,
      "curveFrom": "{0.88794365877514414, 0.18345745099309813}",
      "curveMode": 4,
      "curveTo": "{0.78991839473566305, 0.14022812172628221}",
      "hasCurveFrom": true,
      "hasCurveTo": false,
      "point": "{0.78991839473566305, 0.14022812172628221}"
    },
    {
      "_class": "curvePoint",
      "cornerRadius": 0,
      "curveFrom": "{1.0123603400560219, 0.36423464610887307}",
      "curveMode": 2,
      "curveTo": "{0.95194042878908403, 0.23695274342531744}",
      "hasCurveFrom": true,
      "hasCurveTo": true,
      "point": "{0.98210204849353921, 0.30063379618571001}"
    },
    {
      "_class": "curvePoint",
      "cornerRadius": 0,
      "curveFrom": "{0.9256456834057134, 0.55463618169221407}",
      "curveMode": 3,
      "curveTo": "{1.0042399039817451, 0.43224665207967039}",
      "hasCurveFrom": true,
      "hasCurveTo": true,
      "point": "{0.95783741212873785, 0.5044292055864128}"
    },
    {
      "_class": "curvePoint",
      "cornerRadius": 0,
      "curveFrom": "{0.78518147369233582, 0.63403699054963103}",
      "curveMode": 2,
      "curveTo": "{0.88475348746024962, 0.59056705277112598}",
      "hasCurveFrom": true,
      "hasCurveTo": true,
      "point": "{0.83496748057629278, 0.6123020216603785}"
    },
    {
      "_class": "curvePoint",
      "cornerRadius": 0,
      "curveFrom": "{0.67052865007219375, 0.63435780189854973}",
      "curveMode": 4,
      "curveTo": "{0.73046520204899656, 0.64141565157476466}",
      "hasCurveFrom": false,
      "hasCurveTo": true,
      "point": "{0.67052865007219375, 0.63435780189854973}"
    },
    {
      "_class": "curvePoint",
      "cornerRadius": 0,
      "curveFrom": "{0.67468553996735969, 0.97914979914908984}",
      "curveMode": 4,
      "curveTo": "{0.67487888368341342, 0.9739366147291586}",
      "hasCurveFrom": true,
      "hasCurveTo": false,
      "point": "{0.67487888368341342, 0.9739366147291586}"
    },
    {
      "_class": "curvePoint",
      "cornerRadius": 0,
      "curveFrom": "{0.66724180689927315, 0.99310509282705994}",
      "curveMode": 2,
      "curveTo": "{0.6734288058130069, 0.9834807523594945}",
      "hasCurveFrom": true,
      "hasCurveTo": true,
      "point": "{0.67120535307838392, 0.98692947436037215}"
    },
    {
      "_class": "curvePoint",
      "cornerRadius": 0,
      "curveFrom": "{0.64568398255922976, 1.0007243623638826}",
      "curveMode": 2,
      "curveTo": "{0.66134482355961932, 0.99711523468854546}",
      "hasCurveFrom": true,
      "hasCurveTo": true,
      "point": "{0.65351440305942388, 0.99887969710759961}"
    },
    {
      "_class": "curvePoint",
      "cornerRadius": 0,
      "curveFrom": "{0.63214992243543566, 0.99743604603746472}",
      "curveMode": 4,
      "curveTo": "{0.63862693692325068, 1.0003233481777341}",
      "hasCurveFrom": false,
      "hasCurveTo": true,
      "point": "{0.63214992243543566, 0.99743604603746472}"
    },
    {
      "_class": "curvePoint",
      "cornerRadius": 0,
      "curveFrom": "{0.50957000645707184, 0.94329913090740747}",
      "curveMode": 4,
      "curveTo": "{0.52233069171664825, 0.9489133295134875}",
      "hasCurveFrom": true,
      "hasCurveTo": false,
      "point": "{0.52233069171664825, 0.9489133295134875}"
    },
    {
      "_class": "curvePoint",
      "cornerRadius": 0,
      "curveFrom": "{0.49352247802457344, 0.91963929392464172}",
      "curveMode": 2,
      "curveTo": "{0.50125622666674141, 0.93632148406842264}",
      "hasCurveFrom": true,
      "hasCurveTo": true,
      "point": "{0.49738935234565673, 0.92798038899653246}"
    },
    {
      "_class": "curvePoint",
      "cornerRadius": 0,
      "curveFrom": "{0.49120235343192298, 0.89942817894275418}",
      "curveMode": 4,
      "curveTo": "{0.49139569714797671, 0.91017535913153591}",
      "hasCurveFrom": false,
      "hasCurveTo": true,
      "point": "{0.49120235343192298, 0.89942817894275418}"
    },
    {
      "_class": "curvePoint",
      "cornerRadius": 0,
      "curveFrom": "{0.4951658996110338, 0.5873589392819375}",
      "curveMode": 1,
      "curveTo": "{0.4951658996110338, 0.5873589392819375}",
      "hasCurveFrom": false,
      "hasCurveTo": false,
      "point": "{0.4951658996110338, 0.5873589392819375}"
    },
    {
      "_class": "curvePoint",
      "cornerRadius": 0,
      "curveFrom": "{0.33159711582917878, 0.51501598010073546}",
      "curveMode": 1,
      "curveTo": "{0.33159711582917878, 0.51501598010073546}",
      "hasCurveFrom": false,
      "hasCurveTo": false,
      "point": "{0.33159711582917878, 0.51501598010073546}"
    },
    {
      "_class": "curvePoint",
      "cornerRadius": 0,
      "curveFrom": "{0.16831834762140635, 0.76949958263061735}",
      "curveMode": 4,
      "curveTo": "{0.17257190937459849, 0.76260213862886206}",
      "hasCurveFrom": true,
      "hasCurveTo": false,
      "point": "{0.17257190937459849, 0.76260213862886206}"
    },
    {
      "_class": "curvePoint",
      "cornerRadius": 0,
      "curveFrom": "{0.14434372683068494, 0.77880311174926409}",
      "curveMode": 2,
      "curveTo": "{0.16164798941753616, 0.77415134718994127}",
      "hasCurveFrom": true,
      "hasCurveTo": true,
      "point": "{0.15304419405312433, 0.77647722946960274}"
    },
    {
      "_class": "curvePoint",
      "cornerRadius": 0,
      "curveFrom": "{0.12694279238580752, 0.77423155002717081}",
      "curveMode": 4,
      "curveTo": "{0.13564325960824555, 0.77808128621419725}",
      "hasCurveFrom": false,
      "hasCurveTo": true,
      "point": "{0.12694279238580752, 0.77423155002717081}"
    },
    {
      "_class": "curvePoint",
      "cornerRadius": 0,
      "curveFrom": "{0.0090031255927448088, 0.72209970582785687}",
      "curveMode": 4,
      "curveTo": "{0.017026889808994011, 0.72562863066596406}",
      "hasCurveFrom": true,
      "hasCurveTo": false,
      "point": "{0.017026889808994011, 0.72562863066596406}"
    },
    {
      "_class": "curvePoint",
      "cornerRadius": 0,
      "curveFrom": "{0.001366048808603106, 0.70942765754556203}",
      "curveMode": 4,
      "curveTo": "{0.0037828452592811724, 0.71672611573346601}",
      "hasCurveFrom": false,
      "hasCurveTo": true,
      "point": "{0.001366048808603106, 0.70942765754556203}"
    }
  ],
  "resizingConstraint": 63,
  "resizingType": 0,
  "rotation": 0,
  "shouldBreakMaskChain": false,
  "style": {
    "_class": "style",
    "blur": {
      "_class": "blur",
      "center": "{0.5, 0.5}",
      "isEnabled": false,
      "motionAngle": 0,
      "radius": 2.309347358355248,
      "saturation": 1,
      "type": 0
    },
    "borderOptions": {
      "_class": "borderOptions",
      "dashPattern": [
      ],
      "isEnabled": true,
      "lineCapStyle": 0,
      "lineJoinStyle": 0
    },
    "borders": [
    ],
    "colorControls": {
      "_class": "colorControls",
      "brightness": 0,
      "contrast": 1,
      "hue": 0,
      "isEnabled": false,
      "saturation": 1
    },
    "contextSettings": {
      "_class": "graphicsContextSettings",
      "blendMode": 0,
      "opacity": 1
    },
    "do_objectID": "0F314211-7A5E-426A-B786-A27FC78CC80D",
    "endMarkerType": 0,
    "fills": [
    ],
    "innerShadows": [
    ],
    "miterLimit": 10,
    "shadows": [
    ],
    "startMarkerType": 0,
    "windingRule": 1
  }
}